internetmonitor_client/__init__.py
internetmonitor_client/client.py
internetmonitor_client/py.typed
internetmonitor_client_python-1.0.dist-info/METADATA
internetmonitor_client_python-1.0.dist-info/WHEEL
internetmonitor_client_python-1.0.dist-info/licenses/LICENSE
internetmonitor_client_python-1.0.dist-info/licenses/NOTICE
internetmonitor_client_python-1.0.dist-info/RECORD
