Metadata-Version: 2.3
Name: internetmonitor-client-python
Version: 1.0
Summary: A high-level client representing Amazon CloudWatch Internet Monitor.
Classifier: Development Status :: 5 - Production/Stable
Classifier: Intended Audience :: Developers
Classifier: License :: OSI Approved :: Apache Software License
Classifier: Programming Language :: Python
Classifier: Programming Language :: Python :: 3.11
Requires-Python: >=3.11
Requires-Dist: boto3~=1.35.60
Provides-Extra: test
Requires-Dist: bandit; extra == 'test'
Requires-Dist: mypy; extra == 'test'
Requires-Dist: pytest; extra == 'test'
Requires-Dist: ruff; extra == 'test'
